radios/__init__.py
radios/const.py
radios/exceptions.py
radios/models.py
radios/py.typed
radios/radio_browser.py
radios-0.3.0.dist-info/LICENSE.md
radios-0.3.0.dist-info/METADATA
radios-0.3.0.dist-info/WHEEL
radios-0.3.0.dist-info/RECORD
