Metadata-Version: 2.1
Name: radios
Version: 0.3.0
Summary: Asynchronous Python client for the Radio Browser API
Home-page: https://github.com/frenck/python-radios
License: MIT
Keywords: radio browser,radio,web radio,radios,api,async,client
Author: Franck Nijhof
Author-email: opensource@frenck.dev
Maintainer: Franck Nijhof
Maintainer-email: opensource@frenck.dev
Requires-Python: >=3.11,<4.0
Classifier: Development Status :: 4 - Beta
Classifier: Framework :: AsyncIO
Classifier: Intended Audience :: Developers
Classifier: License :: OSI Approved :: MIT License
Classifier: Natural Language :: English
Classifier: Programming Language :: Python :: 3
Classifier: Programming Language :: Python :: 3.11
Classifier: Programming Language :: Python :: 3.12
Classifier: Topic :: Software Development :: Libraries :: Python Modules
Requires-Dist: aiodns (>=3.0)
Requires-Dist: aiohttp (>=3.0.0)
Requires-Dist: awesomeversion (>=21.10.1)
Requires-Dist: backoff (>=1.9.0)
Requires-Dist: cachetools (>=4.0.0)
Requires-Dist: mashumaro (>=3.10)
Requires-Dist: orjson (>=3.9.8)
Requires-Dist: pycountry (>=22.1.10,<23.0.0)
Requires-Dist: yarl (>=1.6.0)
Project-URL: Bug Tracker, https://github.com/frenck/python-radios/issues
Project-URL: Changelog, https://github.com/frenck/python-radios/releases
Project-URL: Documentation, https://github.com/frenck/python-radios
Project-URL: Repository, https://github.com/frenck/python-radios
